dreye/__init__.py
dreye/err.py
dreye/api/__init__.py
dreye/api/barycentric.py
dreye/api/capture.py
dreye/api/convex.py
dreye/api/defaults.py
dreye/api/domain.py
dreye/api/estimator.py
dreye/api/filter_templates.py
dreye/api/metrics.py
dreye/api/project.py
dreye/api/sampling.py
dreye/api/spherical.py
dreye/api/utils.py
dreye/api/optimize/__init__.py
dreye/api/optimize/lsq_linear.py
dreye/api/optimize/lsq_nonlinear.py
dreye/api/optimize/parallel.py
dreye/api/optimize/utils.py
dreye/api/units/__init__.py
dreye/api/units/convert.py
dreye/api/units/pint.py
dreye/constants/__init__.py
dreye/constants/common.py
dreye/constants/packages.py
dreye/constants/units.py
dreye/core/__init__.py
dreye/core/abstract.py
dreye/core/domain.py
dreye/core/measurement_utils.py
dreye/core/numpy_mixin.py
dreye/core/opsin_template.py
dreye/core/photoreceptor.py
dreye/core/signal.py
dreye/core/signal_container.py
dreye/core/spectral_measurement.py
dreye/core/spectrum_mixin.py
dreye/core/spectrum_utils.py
dreye/datasets/__init__.py
dreye/datasets/flowers.feather
dreye/datasets/flowers.py
dreye/datasets/granada.py
dreye/datasets/granada_daylight.mat
dreye/datasets/human.py
dreye/datasets/linss10e_1.csv
dreye/datasets/linss2_10e_1.csv
dreye/datasets/spitschan2016/__init__.py
dreye/datasets/spitschan2016/spitschan2016.feather
dreye/datasets/spitschan2016/spitschan2016.py
dreye/datasets/spitschan2016/srep26756-s1.csv
dreye/datasets/spitschan2016/srep26756-s2.csv
dreye/datasets/spitschan2016/srep26756-s3.csv
dreye/estimators/__init__.py
dreye/estimators/base.py
dreye/estimators/capture_tests.py
dreye/estimators/dependent_excitation_models.py
dreye/estimators/excitation_models.py
dreye/estimators/intensity_models.py
dreye/estimators/led_substitution.py
dreye/estimators/metric_functions.py
dreye/estimators/metrics.py
dreye/estimators/silent_substitution.py
dreye/estimators/utils.py
dreye/hardware/__init__.py
dreye/hardware/base_spectrometer.py
dreye/hardware/base_system.py
dreye_ext-0.0.1.dist-info/METADATA
dreye_ext-0.0.1.dist-info/WHEEL
dreye_ext-0.0.1.dist-info/top_level.txt
dreye_ext-0.0.1.dist-info/RECORD
